[
  {
    "id": "5dac5b1c4bd3ef78871a77fc",
    "firstName": "Jennifer",
    "lastName": "Short",
    "phoneNumber": "1234567890"
  },
  {
    "id": "5dac5b1c9cb6032aeff4fabb",
    "firstName": "Vicky",
    "lastName": "Macias",
    "phoneNumber": "1234567890"
  },
  {
    "id": "5dac5b1c4199c83eccc489a8",
    "firstName": "Miranda",
    "lastName": "Hammond",
    "phoneNumber": "1234567890"
  },
  {
    "id": "5dac5b1ce45ee74533ad6dc9",
    "firstName": "Newton",
    "lastName": "Rhodes",
    "phoneNumber": "1234567890"
  },
  {
    "id": "5dac5b1c8496ed3ea0f5116c",
    "firstName": "Lamb",
    "lastName": "Schroeder",
    "phoneNumber": "1234567890"
  },
  {
    "id": "5dac5b1c8b666666f8f69e65",
    "firstName": "Connie",
    "lastName": "Bryan",
    "phoneNumber": "1234567890"
  },
  {
    "id": "5dac5b1cc631cc19320e6da7",
    "firstName": "Marguerite",
    "lastName": "Harrington",
    "phoneNumber": "1234567890"
  },
  {
    "id": "5dac5b1c1b9d1ff7af967331",
    "firstName": "Audrey",
    "lastName": "Cunningham",
    "phoneNumber": "1234567890"
  },
  {
    "id": "5dac5b1c5d95b2d9b3db2f1f",
    "firstName": "Dillon",
    "lastName": "Singleton",
    "phoneNumber": "1234567890"
  },
  {
    "id": "5dac5b1c15df3717b55ab505",
    "firstName": "Gracie",
    "lastName": "Riddle",
    "phoneNumber": "1234567890"
  },
  {
    "id": "5dac5b1cb99381272676e13f",
    "firstName": "Janie",
    "lastName": "Harmon",
    "phoneNumber": "1234567890"
  },
  {
    "id": "5dac5b1c6ae3dba0895b33ad",
    "firstName": "Callie",
    "lastName": "Reynolds",
    "phoneNumber": "1234567890"
  },
  {
    "id": "5dac5b1c1ec4ec5b67cce8d0",
    "firstName": "Frank",
    "lastName": "Hansen",
    "phoneNumber": "1234567890"
  },
  {
    "id": "5dac5b1c471bcd3590a3785f",
    "firstName": "Armstrong",
    "lastName": "Frye",
    "phoneNumber": "1234567890"
  },
  {
    "id": "5dac5b1c475b59c4345f1143",
    "firstName": "Scott",
    "lastName": "Skinner",
    "phoneNumber": "1234567890"
  },
  {
    "id": "5dac5b1cb64c492e0975ab64",
    "firstName": "Mcintyre",
    "lastName": "Maddox",
    "phoneNumber": "1234567890"
  },
  {
    "id": "5dac5b1c8b4bc0c67395f9a8",
    "firstName": "Simmons",
    "lastName": "Bonner",
    "phoneNumber": "1234567890"
  },
  {
    "id": "5dac5b1cd1fa55177a11453a",
    "firstName": "Erna",
    "lastName": "Mercer",
    "phoneNumber": "1234567890"
  },
  {
    "id": "5dac5b1c772c893e7e8247ee",
    "firstName": "Cox",
    "lastName": "Kemp",
    "phoneNumber": "1234567890"
  },
  {
    "id": "5dac5b1c39fa84211b296123",
    "firstName": "Sara",
    "lastName": "Osborn",
    "phoneNumber": "1234567890"
  },
  {
    "id": "5dac5b1c6815b672964ac59b",
    "firstName": "Courtney",
    "lastName": "Ramos",
    "phoneNumber": "1234567890"
  },
  {
    "id": "5dac5b1c767f07ab87202601",
    "firstName": "Susie",
    "lastName": "Sharpe",
    "phoneNumber": "1234567890"
  },
  {
    "id": "5dac5b1c982a456e3dbb9b7a",
    "firstName": "Albert",
    "lastName": "Jimenez",
    "phoneNumber": "1234567890"
  },
  {
    "id": "5dac5b1cf750b4268b3fb002",
    "firstName": "Jeannine",
    "lastName": "Blevins",
    "phoneNumber": "1234567890"
  },
  {
    "id": "5dac5b1ca3d761ef98c5911c",
    "firstName": "Penelope",
    "lastName": "Burns",
    "phoneNumber": "1234567890"
  },
  {
    "id": "5dac5b1cdedd6691adfd3dfb",
    "firstName": "Flora",
    "lastName": "Allen",
    "phoneNumber": "1234567890"
  },
  {
    "id": "5dac5b1c396cee3202e731a9",
    "firstName": "Rita",
    "lastName": "Abbott",
    "phoneNumber": "1234567890"
  },
  {
    "id": "5dac5b1c3bff82103c0a325e",
    "firstName": "Branch",
    "lastName": "Mcknight",
    "phoneNumber": "1234567890"
  },
  {
    "id": "5dac5b1cc1237c7b975fa4e8",
    "firstName": "Essie",
    "lastName": "Simpson",
    "phoneNumber": "1234567890"
  },
  {
    "id": "5dac5b1cf24c3b1b3e48db78",
    "firstName": "Skinner",
    "lastName": "Guzman",
    "phoneNumber": "1234567890"
  },
  {
    "id": "5dac5b1c160986360c943142",
    "firstName": "Dawn",
    "lastName": "Avila",
    "phoneNumber": "1234567890"
  },
  {
    "id": "5dac5b1cfb316be1ccb9d2ba",
    "firstName": "Avila",
    "lastName": "Richardson",
    "phoneNumber": "1234567890"
  },
  {
    "id": "5dac5b1c055a7839d8169740",
    "firstName": "Kris",
    "lastName": "Vaughn",
    "phoneNumber": "1234567890"
  },
  {
    "id": "5dac5b1cd17882644753ae35",
    "firstName": "Estrada",
    "lastName": "Collins",
    "phoneNumber": "1234567890"
  },
  {
    "id": "5dac5b1cc90b259401120a8e",
    "firstName": "Lillian",
    "lastName": "Arnold",
    "phoneNumber": "1234567890"
  },
  {
    "id": "5dac5b1c4a9efc93d7dcca84",
    "firstName": "Dickson",
    "lastName": "Cruz",
    "phoneNumber": "1234567890"
  },
  {
    "id": "5dac5b1c5f720c96f6d508b2",
    "firstName": "Rosa",
    "lastName": "Dunlap",
    "phoneNumber": "1234567890"
  },
  {
    "id": "5dac5b1c68244c8ecfbbfcd9",
    "firstName": "Lakisha",
    "lastName": "Davis",
    "phoneNumber": "1234567890"
  },
  {
    "id": "5dac5b1c30b01559b1b4c6c5",
    "firstName": "Aileen",
    "lastName": "Velasquez",
    "phoneNumber": "1234567890"
  },
  {
    "id": "5dac5b1c747f27ee2ced53bf",
    "firstName": "Mcpherson",
    "lastName": "Mcmahon",
    "phoneNumber": "1234567890"
  },
  {
    "id": "5dac5b1cee3768cc6ef99a96",
    "firstName": "Jessica",
    "lastName": "Mccray",
    "phoneNumber": "1234567890"
  },
  {
    "id": "5dac5b1c21adf236d0bba40f",
    "firstName": "Carolina",
    "lastName": "Rosario",
    "phoneNumber": "1234567890"
  },
  {
    "id": "5dac5b1c54813bbdd36ba9d2",
    "firstName": "Bridget",
    "lastName": "Melendez",
    "phoneNumber": "1234567890"
  },
  {
    "id": "5dac5b1ccc51bd81fcace74a",
    "firstName": "Myrtle",
    "lastName": "Lang",
    "phoneNumber": "1234567890"
  },
  {
    "id": "5dac5b1c198b25e4cfe531f4",
    "firstName": "Richardson",
    "lastName": "Mckinney",
    "phoneNumber": "1234567890"
  },
  {
    "id": "5dac5b1c7da20ba8d89138c7",
    "firstName": "Dodson",
    "lastName": "Haynes",
    "phoneNumber": "1234567890"
  },
  {
    "id": "5dac5b1ce3979f4b582fd1c6",
    "firstName": "Paula",
    "lastName": "Mcfadden",
    "phoneNumber": "1234567890"
  },
  {
    "id": "5dac5b1c462feb6feb7805a3",
    "firstName": "Marci",
    "lastName": "Goodwin",
    "phoneNumber": "1234567890"
  },
  {
    "id": "5dac5b1c6da9eb11562ac1cc",
    "firstName": "Jayne",
    "lastName": "Sykes",
    "phoneNumber": "1234567890"
  },
  {
    "id": "5dac5b1c665ebcc267abebc4",
    "firstName": "Kim",
    "lastName": "Gutierrez",
    "phoneNumber": "1234567890"
  },
  {
    "id": "5dac5b1ca1fd730d9c64131c",
    "firstName": "Cantrell",
    "lastName": "Hampton",
    "phoneNumber": "1234567890"
  },
  {
    "id": "5dac5b1cb4efde367b54394e",
    "firstName": "Nicole",
    "lastName": "Juarez",
    "phoneNumber": "1234567890"
  },
  {
    "id": "5dac5b1c48a00fdbe9d2d9de",
    "firstName": "Roberts",
    "lastName": "Pollard",
    "phoneNumber": "1234567890"
  },
  {
    "id": "5dac5b1c52f66ebb11ec86e4",
    "firstName": "Melba",
    "lastName": "Foster",
    "phoneNumber": "1234567890"
  },
  {
    "id": "5dac5b1c8c45995100766277",
    "firstName": "Petty",
    "lastName": "Sharp",
    "phoneNumber": "1234567890"
  },
  {
    "id": "5dac5b1c2c695e12d5cb2a29",
    "firstName": "Brandie",
    "lastName": "Wright",
    "phoneNumber": "1234567890"
  },
  {
    "id": "5dac5b1c7ff775691c79df3a",
    "firstName": "Reilly",
    "lastName": "Miles",
    "phoneNumber": "1234567890"
  },
  {
    "id": "5dac5b1cd8d5e9da6d25d131",
    "firstName": "Richard",
    "lastName": "Matthews",
    "phoneNumber": "1234567890"
  },
  {
    "id": "5dac5b1ca168a3e954891d80",
    "firstName": "Craig",
    "lastName": "Long",
    "phoneNumber": "1234567890"
  },
  {
    "id": "5dac5b1c632bbc9705f48e7c",
    "firstName": "Delia",
    "lastName": "Talley",
    "phoneNumber": "1234567890"
  },
  {
    "id": "5dac5b1c49b60a2d3e396edd",
    "firstName": "Wilcox",
    "lastName": "Giles",
    "phoneNumber": "1234567890"
  },
  {
    "id": "5dac5b1cf3b2c13eae78a36f",
    "firstName": "Francisca",
    "lastName": "Howard",
    "phoneNumber": "1234567890"
  },
  {
    "id": "5dac5b1cc43d933ef8bbf185",
    "firstName": "Marissa",
    "lastName": "Warner",
    "phoneNumber": "1234567890"
  },
  {
    "id": "5dac5b1cb486bd17c0b04b77",
    "firstName": "Sandy",
    "lastName": "Vincent",
    "phoneNumber": "1234567890"
  },
  {
    "id": "5dac5b1ca02409c150848d3b",
    "firstName": "Ross",
    "lastName": "Valenzuela",
    "phoneNumber": "1234567890"
  },
  {
    "id": "5dac5b1c4bed711a1591877d",
    "firstName": "Ada",
    "lastName": "Lester",
    "phoneNumber": "1234567890"
  },
  {
    "id": "5dac5b1c4afcbaf8ef4f58c3",
    "firstName": "Lott",
    "lastName": "Benton",
    "phoneNumber": "1234567890"
  },
  {
    "id": "5dac5b1ce3feb5f163f712ae",
    "firstName": "Nicholson",
    "lastName": "French",
    "phoneNumber": "1234567890"
  },
  {
    "id": "5dac5b1cef9aa82df2e6492e",
    "firstName": "Beasley",
    "lastName": "Glover",
    "phoneNumber": "1234567890"
  },
  {
    "id": "5dac5b1c9a3f693e6285e048",
    "firstName": "Monique",
    "lastName": "Albert",
    "phoneNumber": "1234567890"
  },
  {
    "id": "5dac5b1ca9d5ed419fc2e0be",
    "firstName": "Tammy",
    "lastName": "Palmer",
    "phoneNumber": "1234567890"
  },
  {
    "id": "5dac5b1ceb6015aad5e2d116",
    "firstName": "Kline",
    "lastName": "Hays",
    "phoneNumber": "1234567890"
  },
  {
    "id": "5dac5b1c4c271a2bbc0e87c2",
    "firstName": "Sykes",
    "lastName": "Santiago",
    "phoneNumber": "1234567890"
  },
  {
    "id": "5dac5b1c558f75c601821a6a",
    "firstName": "Mona",
    "lastName": "Franco",
    "phoneNumber": "1234567890"
  },
  {
    "id": "5dac5b1c1b6822ae8fcf6cb5",
    "firstName": "Juliana",
    "lastName": "Calderon",
    "phoneNumber": "1234567890"
  },
  {
    "id": "5dac5b1c7656caf74ed5ea45",
    "firstName": "Trujillo",
    "lastName": "Clements",
    "phoneNumber": "1234567890"
  },
  {
    "id": "5dac5b1c41ccfef6455829b1",
    "firstName": "Latonya",
    "lastName": "Guy",
    "phoneNumber": "1234567890"
  },
  {
    "id": "5dac5b1c057e970e8210f7d5",
    "firstName": "Cohen",
    "lastName": "Booth",
    "phoneNumber": "1234567890"
  },
  {
    "id": "5dac5b1cf37fc8d4f5a02a6e",
    "firstName": "Carissa",
    "lastName": "Pate",
    "phoneNumber": "1234567890"
  },
  {
    "id": "5dac5b1c64b0cfee869b8dec",
    "firstName": "Weaver",
    "lastName": "Wilkins",
    "phoneNumber": "1234567890"
  },
  {
    "id": "5dac5b1c954d6212a0122eaa",
    "firstName": "Vinson",
    "lastName": "Lamb",
    "phoneNumber": "1234567890"
  },
  {
    "id": "5dac5b1c3a23c573358d225f",
    "firstName": "Moore",
    "lastName": "Mullins",
    "phoneNumber": "1234567890"
  },
  {
    "id": "5dac5b1cb13e46c4cdfefa7b",
    "firstName": "Dolores",
    "lastName": "Webb",
    "phoneNumber": "1234567890"
  },
  {
    "id": "5dac5b1c6ced0ca6e37c4774",
    "firstName": "Sullivan",
    "lastName": "Lambert",
    "phoneNumber": "1234567890"
  },
  {
    "id": "5dac5b1cc171e5743ac0a9ee",
    "firstName": "Rodriquez",
    "lastName": "Foley",
    "phoneNumber": "1234567890"
  },
  {
    "id": "5dac5b1cf0227315ad4704a3",
    "firstName": "Amy",
    "lastName": "Underwood",
    "phoneNumber": "1234567890"
  },
  {
    "id": "5dac5b1c8bf7783393f49538",
    "firstName": "Magdalena",
    "lastName": "Humphrey",
    "phoneNumber": "1234567890"
  },
  {
    "id": "5dac5b1cd835b5acb9b70ca6",
    "firstName": "Alexander",
    "lastName": "Cherry",
    "phoneNumber": "1234567890"
  },
  {
    "id": "5dac5b1c884e6c46c0f6a8c7",
    "firstName": "Castaneda",
    "lastName": "Owens",
    "phoneNumber": "1234567890"
  },
  {
    "id": "5dac5b1cf74f9bf9a984bea7",
    "firstName": "Phillips",
    "lastName": "Coleman",
    "phoneNumber": "1234567890"
  },
  {
    "id": "5dac5b1c860b9183e8f09e3a",
    "firstName": "Delacruz",
    "lastName": "Gamble",
    "phoneNumber": "1234567890"
  },
  {
    "id": "5dac5b1ce541f329d891b7b4",
    "firstName": "Bernard",
    "lastName": "Walsh",
    "phoneNumber": "1234567890"
  },
  {
    "id": "5dac5b1cbcac38cb4a3f20f5",
    "firstName": "Shepard",
    "lastName": "Medina",
    "phoneNumber": "1234567890"
  },
  {
    "id": "5dac5b1c3b5c533912723594",
    "firstName": "Lily",
    "lastName": "Bender",
    "phoneNumber": "1234567890"
  },
  {
    "id": "5dac5b1c163e0e0045a09f56",
    "firstName": "Michael",
    "lastName": "Moreno",
    "phoneNumber": "1234567890"
  },
  {
    "id": "5dac5b1cc2a94897a705c2e1",
    "firstName": "Ford",
    "lastName": "Houston",
    "phoneNumber": "1234567890"
  },
  {
    "id": "5dac5b1c37d2e99350e4d888",
    "firstName": "Jami",
    "lastName": "Caldwell",
    "phoneNumber": "1234567890"
  },
  {
    "id": "5dac5b1cd82971322bfc7013",
    "firstName": "Greer",
    "lastName": "Barlow",
    "phoneNumber": "1234567890"
  },
  {
    "id": "5dac5b1c5f219137c813c885",
    "firstName": "Audra",
    "lastName": "Bridges",
    "phoneNumber": "1234567890"
  },
  {
    "id": "5dac5b1c682ae77f34321f9d",
    "firstName": "Jackson",
    "lastName": "Barr",
    "phoneNumber": "1234567890"
  },
  {
    "id": "5dac5b1c0fea8a9f29da757d",
    "firstName": "Jacqueline",
    "lastName": "Parsons",
    "phoneNumber": "1234567890"
  },
  {
    "id": "5dac5b1c38b56b15777a5380",
    "firstName": "Diane",
    "lastName": "Hensley",
    "phoneNumber": "1234567890"
  },
  {
    "id": "5dac5b1c3d87347c73c4e7d0",
    "firstName": "Savage",
    "lastName": "Dodson",
    "phoneNumber": "1234567890"
  },
  {
    "id": "5dac5b1c10280d3a30c07b30",
    "firstName": "Sheena",
    "lastName": "Baker",
    "phoneNumber": "1234567890"
  },
  {
    "id": "5dac5b1c738c631b9ca62def",
    "firstName": "Byers",
    "lastName": "Park",
    "phoneNumber": "1234567890"
  },
  {
    "id": "5dac5b1c3b82c879e98fa80d",
    "firstName": "Santiago",
    "lastName": "Curtis",
    "phoneNumber": "1234567890"
  },
  {
    "id": "5dac5b1c2075f280a7e1b825",
    "firstName": "Oneill",
    "lastName": "Stuart",
    "phoneNumber": "1234567890"
  },
  {
    "id": "5dac5b1c31e548e9e224fe3d",
    "firstName": "Britt",
    "lastName": "Roy",
    "phoneNumber": "1234567890"
  },
  {
    "id": "5dac5b1c7dfe5d58f16c9a5f",
    "firstName": "Beverly",
    "lastName": "Sexton",
    "phoneNumber": "1234567890"
  },
  {
    "id": "5dac5b1c4d3528a9b77fcdf5",
    "firstName": "Hess",
    "lastName": "Cooke",
    "phoneNumber": "1234567890"
  },
  {
    "id": "5dac5b1cfb3fca3a485caccf",
    "firstName": "Gina",
    "lastName": "Newman",
    "phoneNumber": "1234567890"
  },
  {
    "id": "5dac5b1ccf8edb9433b0b4b2",
    "firstName": "Mercer",
    "lastName": "Riggs",
    "phoneNumber": "1234567890"
  },
  {
    "id": "5dac5b1ce49b2f062a24a484",
    "firstName": "Knowles",
    "lastName": "Barron",
    "phoneNumber": "1234567890"
  },
  {
    "id": "5dac5b1cc1e80d4ceca49bc5",
    "firstName": "Humphrey",
    "lastName": "Cabrera",
    "phoneNumber": "1234567890"
  },
  {
    "id": "5dac5b1c25e054494f0b7551",
    "firstName": "Liz",
    "lastName": "Parrish",
    "phoneNumber": "1234567890"
  },
  {
    "id": "5dac5b1c422dbc126a85adf8",
    "firstName": "Benton",
    "lastName": "Hughes",
    "phoneNumber": "1234567890"
  },
  {
    "id": "5dac5b1c93d1b6feddd2ba53",
    "firstName": "Kathrine",
    "lastName": "Trujillo",
    "phoneNumber": "1234567890"
  },
  {
    "id": "5dac5b1cbf33d937a0269464",
    "firstName": "Conrad",
    "lastName": "Bolton",
    "phoneNumber": "1234567890"
  },
  {
    "id": "5dac5b1c329a06ae8b6f1cd5",
    "firstName": "Gordon",
    "lastName": "Briggs",
    "phoneNumber": "1234567890"
  },
  {
    "id": "5dac5b1c52b3649262e479b8",
    "firstName": "Tran",
    "lastName": "Padilla",
    "phoneNumber": "1234567890"
  },
  {
    "id": "5dac5b1caab70b6eef9f0531",
    "firstName": "Duke",
    "lastName": "Glenn",
    "phoneNumber": "1234567890"
  },
  {
    "id": "5dac5b1c45a7a9b424598eee",
    "firstName": "Anastasia",
    "lastName": "Hickman",
    "phoneNumber": "1234567890"
  },
  {
    "id": "5dac5b1cb6a6a4e0dc0dfa30",
    "firstName": "Rae",
    "lastName": "Odonnell",
    "phoneNumber": "1234567890"
  },
  {
    "id": "5dac5b1c9a2e7dbf38c25eb5",
    "firstName": "Freeman",
    "lastName": "Nixon",
    "phoneNumber": "1234567890"
  },
  {
    "id": "5dac5b1c3703a40efb85130f",
    "firstName": "Douglas",
    "lastName": "Barnes",
    "phoneNumber": "1234567890"
  },
  {
    "id": "5dac5b1cc1205819b09db08b",
    "firstName": "Massey",
    "lastName": "Stafford",
    "phoneNumber": "1234567890"
  },
  {
    "id": "5dac5b1c780f7121c74b8d77",
    "firstName": "Eve",
    "lastName": "Dalton",
    "phoneNumber": "1234567890"
  },
  {
    "id": "5dac5b1cae67a04aac097d28",
    "firstName": "Morrow",
    "lastName": "Potter",
    "phoneNumber": "1234567890"
  },
  {
    "id": "5dac5b1cde271db4bee3427b",
    "firstName": "Emerson",
    "lastName": "Perez",
    "phoneNumber": "1234567890"
  },
  {
    "id": "5dac5b1c7d7a16b47045c880",
    "firstName": "Cindy",
    "lastName": "Langley",
    "phoneNumber": "1234567890"
  },
  {
    "id": "5dac5b1c90e141fe0d436b51",
    "firstName": "Eva",
    "lastName": "Phillips",
    "phoneNumber": "1234567890"
  },
  {
    "id": "5dac5b1cafe188b7feda57dd",
    "firstName": "Harris",
    "lastName": "Hall",
    "phoneNumber": "1234567890"
  },
  {
    "id": "5dac5b1c5871a0c3eb7a6d85",
    "firstName": "Maura",
    "lastName": "Jefferson",
    "phoneNumber": "1234567890"
  },
  {
    "id": "5dac5b1c8c1b63ce7865fd1b",
    "firstName": "Lawrence",
    "lastName": "Silva",
    "phoneNumber": "1234567890"
  },
  {
    "id": "5dac5b1cd43e1bd9262d9888",
    "firstName": "Klein",
    "lastName": "Bird",
    "phoneNumber": "1234567890"
  },
  {
    "id": "5dac5b1c6d7805b74ea81da8",
    "firstName": "Hutchinson",
    "lastName": "Brown",
    "phoneNumber": "1234567890"
  },
  {
    "id": "5dac5b1c96f04b1d9b32be8a",
    "firstName": "Jefferson",
    "lastName": "Witt",
    "phoneNumber": "1234567890"
  },
  {
    "id": "5dac5b1cf230f899b1485743",
    "firstName": "Lorrie",
    "lastName": "Alexander",
    "phoneNumber": "1234567890"
  },
  {
    "id": "5dac5b1c3c43260c65983d1f",
    "firstName": "Amanda",
    "lastName": "Fulton",
    "phoneNumber": "1234567890"
  },
  {
    "id": "5dac5b1cd24897f3f72006c9",
    "firstName": "Zamora",
    "lastName": "Rocha",
    "phoneNumber": "1234567890"
  },
  {
    "id": "5dac5b1c3c7db5f705631133",
    "firstName": "Johnnie",
    "lastName": "Puckett",
    "phoneNumber": "1234567890"
  },
  {
    "id": "5dac5b1cc9fcb0bb79548002",
    "firstName": "Margret",
    "lastName": "Acevedo",
    "phoneNumber": "1234567890"
  },
  {
    "id": "5dac5b1ce32964d336c92548",
    "firstName": "Henrietta",
    "lastName": "Montoya",
    "phoneNumber": "1234567890"
  },
  {
    "id": "5dac5b1c41bdf95e58d712a6",
    "firstName": "Hale",
    "lastName": "Wilkerson",
    "phoneNumber": "1234567890"
  },
  {
    "id": "5dac5b1c0fa1a9202cfe14dd",
    "firstName": "Fern",
    "lastName": "Berry",
    "phoneNumber": "1234567890"
  },
  {
    "id": "5dac5b1ca98a6bf7839da719",
    "firstName": "Krystal",
    "lastName": "Decker",
    "phoneNumber": "1234567890"
  },
  {
    "id": "5dac5b1ca7612ddb83ced7ab",
    "firstName": "Greene",
    "lastName": "Petersen",
    "phoneNumber": "1234567890"
  },
  {
    "id": "5dac5b1c7679a7c0f189b1f5",
    "firstName": "Martha",
    "lastName": "Barker",
    "phoneNumber": "1234567890"
  },
  {
    "id": "5dac5b1c36d6a8892b6a69e6",
    "firstName": "Molina",
    "lastName": "Nunez",
    "phoneNumber": "1234567890"
  },
  {
    "id": "5dac5b1c480b5197c5a9107e",
    "firstName": "Jolene",
    "lastName": "Lowery",
    "phoneNumber": "1234567890"
  },
  {
    "id": "5dac5b1c49aa740f22edcaba",
    "firstName": "Ina",
    "lastName": "Spence",
    "phoneNumber": "1234567890"
  },
  {
    "id": "5dac5b1ca5b0b80e6e6ec708",
    "firstName": "Wooten",
    "lastName": "Tyson",
    "phoneNumber": "1234567890"
  },
  {
    "id": "5dac5b1cb1acec8f5cf83ded",
    "firstName": "Stacy",
    "lastName": "Williamson",
    "phoneNumber": "1234567890"
  },
  {
    "id": "5dac5b1c20c034fac27636c7",
    "firstName": "Althea",
    "lastName": "Parker",
    "phoneNumber": "1234567890"
  },
  {
    "id": "5dac5b1c5a3e47343416e39f",
    "firstName": "Kathie",
    "lastName": "Zamora",
    "phoneNumber": "1234567890"
  },
  {
    "id": "5dac5b1c86643618055d7739",
    "firstName": "Barrett",
    "lastName": "Haney",
    "phoneNumber": "1234567890"
  },
  {
    "id": "5dac5b1c8c2c39f4e48bd23b",
    "firstName": "Whitfield",
    "lastName": "Curry",
    "phoneNumber": "1234567890"
  },
  {
    "id": "5dac5b1cc8e873d4853cb9d1",
    "firstName": "Paige",
    "lastName": "Cortez",
    "phoneNumber": "1234567890"
  },
  {
    "id": "5dac5b1ce642550b74e46b92",
    "firstName": "Norman",
    "lastName": "Rodriguez",
    "phoneNumber": "1234567890"
  },
  {
    "id": "5dac5b1c446089394fb48fe6",
    "firstName": "Camacho",
    "lastName": "Rush",
    "phoneNumber": "1234567890"
  },
  {
    "id": "5dac5b1c545317f1ae8bac31",
    "firstName": "Esperanza",
    "lastName": "Mccoy",
    "phoneNumber": "1234567890"
  },
  {
    "id": "5dac5b1cb78b98c3b37916c0",
    "firstName": "Raquel",
    "lastName": "Nash",
    "phoneNumber": "1234567890"
  },
  {
    "id": "5dac5b1cc79354bbeada369d",
    "firstName": "Strong",
    "lastName": "Rodriquez",
    "phoneNumber": "1234567890"
  },
  {
    "id": "5dac5b1c962b3c7eade85c49",
    "firstName": "Luella",
    "lastName": "Slater",
    "phoneNumber": "1234567890"
  },
  {
    "id": "5dac5b1c0a5e20092bd069de",
    "firstName": "Sasha",
    "lastName": "Combs",
    "phoneNumber": "1234567890"
  },
  {
    "id": "5dac5b1c99688157f19e36b4",
    "firstName": "Vonda",
    "lastName": "Nicholson",
    "phoneNumber": "1234567890"
  },
  {
    "id": "5dac5b1c65695cbf3d5ab74a",
    "firstName": "Bridgette",
    "lastName": "Hewitt",
    "phoneNumber": "1234567890"
  },
  {
    "id": "5dac5b1cd9067de4e7914115",
    "firstName": "Garrett",
    "lastName": "Hopper",
    "phoneNumber": "1234567890"
  },
  {
    "id": "5dac5b1cc8a38a75bfdb77a0",
    "firstName": "Shari",
    "lastName": "Lawrence",
    "phoneNumber": "1234567890"
  },
  {
    "id": "5dac5b1cc3dcbbdee7815f52",
    "firstName": "Sondra",
    "lastName": "Simmons",
    "phoneNumber": "1234567890"
  },
  {
    "id": "5dac5b1cb16d9876a9727b35",
    "firstName": "Maribel",
    "lastName": "Reyes",
    "phoneNumber": "1234567890"
  },
  {
    "id": "5dac5b1c433c9eadd6f2ca62",
    "firstName": "Allison",
    "lastName": "Hess",
    "phoneNumber": "1234567890"
  },
  {
    "id": "5dac5b1cd76c452ca194692a",
    "firstName": "Guerra",
    "lastName": "Zimmerman",
    "phoneNumber": "1234567890"
  },
  {
    "id": "5dac5b1c52acd768867961fc",
    "firstName": "Lilly",
    "lastName": "Sheppard",
    "phoneNumber": "1234567890"
  },
  {
    "id": "5dac5b1cbd80a981c42a0c9f",
    "firstName": "Rosetta",
    "lastName": "Santos",
    "phoneNumber": "1234567890"
  },
  {
    "id": "5dac5b1cad4cb5cfa4834d54",
    "firstName": "Alvarez",
    "lastName": "Barton",
    "phoneNumber": "1234567890"
  },
  {
    "id": "5dac5b1cd30374cb0741f4cc",
    "firstName": "Ginger",
    "lastName": "Rodgers",
    "phoneNumber": "1234567890"
  },
  {
    "id": "5dac5b1c95f00b25c10fbf4b",
    "firstName": "Shaffer",
    "lastName": "Head",
    "phoneNumber": "1234567890"
  },
  {
    "id": "5dac5b1c15f17a82e9db048d",
    "firstName": "Juarez",
    "lastName": "Horne",
    "phoneNumber": "1234567890"
  },
  {
    "id": "5dac5b1c56b06c07f91428bc",
    "firstName": "Lucas",
    "lastName": "Callahan",
    "phoneNumber": "1234567890"
  },
  {
    "id": "5dac5b1cdec08c995e1eb1c9",
    "firstName": "Mitzi",
    "lastName": "Cox",
    "phoneNumber": "1234567890"
  },
  {
    "id": "5dac5b1c73c34da5017894f0",
    "firstName": "Rachel",
    "lastName": "Andrews",
    "phoneNumber": "1234567890"
  },
  {
    "id": "5dac5b1c29c44c7cb87d8798",
    "firstName": "Wong",
    "lastName": "Dillard",
    "phoneNumber": "1234567890"
  },
  {
    "id": "5dac5b1ce1770da02494034b",
    "firstName": "Hanson",
    "lastName": "Freeman",
    "phoneNumber": "1234567890"
  },
  {
    "id": "5dac5b1c7fa22b95f02906f1",
    "firstName": "Stella",
    "lastName": "Rios",
    "phoneNumber": "1234567890"
  },
  {
    "id": "5dac5b1c8fa46abb23ac7481",
    "firstName": "Blake",
    "lastName": "Knapp",
    "phoneNumber": "1234567890"
  },
  {
    "id": "5dac5b1cbe9cfb2e8f557cdb",
    "firstName": "Concepcion",
    "lastName": "Lancaster",
    "phoneNumber": "1234567890"
  },
  {
    "id": "5dac5b1c2a66dec8627c66ca",
    "firstName": "Ortega",
    "lastName": "Watts",
    "phoneNumber": "1234567890"
  },
  {
    "id": "5dac5b1c77536ea02470ad5b",
    "firstName": "Carlson",
    "lastName": "Hudson",
    "phoneNumber": "1234567890"
  },
  {
    "id": "5dac5b1cdc8448436e7b5885",
    "firstName": "Ursula",
    "lastName": "Carney",
    "phoneNumber": "1234567890"
  },
  {
    "id": "5dac5b1c6e0500a33092a927",
    "firstName": "Sophia",
    "lastName": "Hahn",
    "phoneNumber": "1234567890"
  },
  {
    "id": "5dac5b1c3f310bfa5553990a",
    "firstName": "Irene",
    "lastName": "David",
    "phoneNumber": "1234567890"
  },
  {
    "id": "5dac5b1c72e2e83af36ca4c5",
    "firstName": "Irwin",
    "lastName": "Watkins",
    "phoneNumber": "1234567890"
  },
  {
    "id": "5dac5b1cc21ab0ccaf5fd7b9",
    "firstName": "Jeannie",
    "lastName": "Moran",
    "phoneNumber": "1234567890"
  },
  {
    "id": "5dac5b1c08aba81b16fc8f2b",
    "firstName": "Andrews",
    "lastName": "Greene",
    "phoneNumber": "1234567890"
  },
  {
    "id": "5dac5b1cbb8cf437485f8cc7",
    "firstName": "Alta",
    "lastName": "Ramirez",
    "phoneNumber": "1234567890"
  },
  {
    "id": "5dac5b1ca20422bc8caf7ce9",
    "firstName": "Blankenship",
    "lastName": "Boyd",
    "phoneNumber": "1234567890"
  },
  {
    "id": "5dac5b1cdf0969786b9d46c1",
    "firstName": "Pope",
    "lastName": "Weaver",
    "phoneNumber": "1234567890"
  },
  {
    "id": "5dac5b1c8e5f71e1a6df79a6",
    "firstName": "Henson",
    "lastName": "Melton",
    "phoneNumber": "1234567890"
  },
  {
    "id": "5dac5b1c41e58a1127fbf715",
    "firstName": "Galloway",
    "lastName": "Soto",
    "phoneNumber": "1234567890"
  },
  {
    "id": "5dac5b1c596eb4a030bc93a8",
    "firstName": "Crosby",
    "lastName": "Wynn",
    "phoneNumber": "1234567890"
  },
  {
    "id": "5dac5b1c36d64d7da9b222d2",
    "firstName": "Whitehead",
    "lastName": "Dixon",
    "phoneNumber": "1234567890"
  },
  {
    "id": "5dac5b1c6987aa0d8d9bd054",
    "firstName": "Reese",
    "lastName": "Stevenson",
    "phoneNumber": "1234567890"
  },
  {
    "id": "5dac5b1c140baa94181a3de6",
    "firstName": "Raymond",
    "lastName": "Walton",
    "phoneNumber": "1234567890"
  },
  {
    "id": "5dac5b1c2d188628d75352d8",
    "firstName": "Hood",
    "lastName": "Hood",
    "phoneNumber": "1234567890"
  },
  {
    "id": "5dac5b1c0f544b48c5e727c0",
    "firstName": "Angelina",
    "lastName": "Raymond",
    "phoneNumber": "1234567890"
  },
  {
    "id": "5dac5b1c3830c1a59cc58945",
    "firstName": "Robinson",
    "lastName": "Landry",
    "phoneNumber": "1234567890"
  },
  {
    "id": "5dac5b1ccd724778d48c6ed3",
    "firstName": "Trevino",
    "lastName": "Rogers",
    "phoneNumber": "1234567890"
  },
  {
    "id": "5dac5b1c7310159f4c356440",
    "firstName": "Donovan",
    "lastName": "Trevino",
    "phoneNumber": "1234567890"
  },
  {
    "id": "5dac5b1c19b50ae06bd68947",
    "firstName": "Haley",
    "lastName": "Mack",
    "phoneNumber": "1234567890"
  },
  {
    "id": "5dac5b1c37a69155bea6c389",
    "firstName": "Eloise",
    "lastName": "Copeland",
    "phoneNumber": "1234567890"
  },
  {
    "id": "5dac5b1cf177f329330de54b",
    "firstName": "Deann",
    "lastName": "Ayala",
    "phoneNumber": "1234567890"
  },
  {
    "id": "5dac5b1c6791dd8ccd1e84e2",
    "firstName": "Higgins",
    "lastName": "Mejia",
    "phoneNumber": "1234567890"
  },
  {
    "id": "5dac5b1c11d272a64588a64e",
    "firstName": "Arnold",
    "lastName": "Sherman",
    "phoneNumber": "1234567890"
  },
  {
    "id": "5dac5b1cefbcaaef4c59b936",
    "firstName": "Flowers",
    "lastName": "Davidson",
    "phoneNumber": "1234567890"
  },
  {
    "id": "5dac5b1c5d2019baf2eaabbc",
    "firstName": "Yates",
    "lastName": "Morrison",
    "phoneNumber": "1234567890"
  },
  {
    "id": "5dac5b1cbd65d6286b84cc4a",
    "firstName": "Jewel",
    "lastName": "Fischer",
    "phoneNumber": "1234567890"
  },
  {
    "id": "5dac5b1c47490203c8536439",
    "firstName": "Myrna",
    "lastName": "Casey",
    "phoneNumber": "1234567890"
  },
  {
    "id": "5dac5b1c72afdf48d12505a6",
    "firstName": "Lynne",
    "lastName": "Hunter",
    "phoneNumber": "1234567890"
  },
  {
    "id": "5dac5b1ca1929edd3f0a2003",
    "firstName": "Beck",
    "lastName": "West",
    "phoneNumber": "1234567890"
  },
  {
    "id": "5dac5b1cdb481efc7140e8f7",
    "firstName": "Vilma",
    "lastName": "Franklin",
    "phoneNumber": "1234567890"
  },
  {
    "id": "5dac5b1c714935a815c066b8",
    "firstName": "Helen",
    "lastName": "Kline",
    "phoneNumber": "1234567890"
  },
  {
    "id": "5dac5b1ca4f0b27aa9e18988",
    "firstName": "Lopez",
    "lastName": "Cross",
    "phoneNumber": "1234567890"
  },
  {
    "id": "5dac5b1c8d030e9e06cfc93b",
    "firstName": "Neal",
    "lastName": "Kerr",
    "phoneNumber": "1234567890"
  },
  {
    "id": "5dac5b1cc9259e7045ce75d2",
    "firstName": "Lolita",
    "lastName": "Banks",
    "phoneNumber": "1234567890"
  },
  {
    "id": "5dac5b1c3021a4dbb64717a4",
    "firstName": "Shannon",
    "lastName": "Farley",
    "phoneNumber": "1234567890"
  },
  {
    "id": "5dac5b1c6846645b88b1c004",
    "firstName": "Rosella",
    "lastName": "Ratliff",
    "phoneNumber": "1234567890"
  },
  {
    "id": "5dac5b1c2999e98ca8da88ae",
    "firstName": "Elaine",
    "lastName": "Edwards",
    "phoneNumber": "1234567890"
  },
  {
    "id": "5dac5b1cca05b240b5fdadd7",
    "firstName": "Tucker",
    "lastName": "Madden",
    "phoneNumber": "1234567890"
  },
  {
    "id": "5dac5b1cdedf43c26e751b39",
    "firstName": "Vasquez",
    "lastName": "Kim",
    "phoneNumber": "1234567890"
  },
  {
    "id": "5dac5b1c9fc29799fc7b56fa",
    "firstName": "Jerri",
    "lastName": "Fields",
    "phoneNumber": "1234567890"
  },
  {
    "id": "5dac5b1c9cbf7841ea1febe1",
    "firstName": "Joni",
    "lastName": "Gonzales",
    "phoneNumber": "1234567890"
  },
  {
    "id": "5dac5b1c4a274c8bd8bf03d6",
    "firstName": "Vega",
    "lastName": "Peterson",
    "phoneNumber": "1234567890"
  },
  {
    "id": "5dac5b1cfe859406102850c2",
    "firstName": "Phoebe",
    "lastName": "Crane",
    "phoneNumber": "1234567890"
  }
]